mmp_metadata_client/__init__.py
mmp_metadata_client/api_client.py
mmp_metadata_client/configuration.py
mmp_metadata_client/exceptions.py
mmp_metadata_client/rest.py
mmp_metadata_client/api/__init__.py
mmp_metadata_client/api/artifact_api.py
mmp_metadata_client/api/execution_api.py
mmp_metadata_client/api/experiment_api.py
mmp_metadata_client/api/run_api.py
mmp_metadata_client/api/trace_api.py
mmp_metadata_client/api/workflow_api.py
mmp_metadata_client/models/__init__.py
mmp_metadata_client/models/artifact.py
mmp_metadata_client/models/dataset.py
mmp_metadata_client/models/event.py
mmp_metadata_client/models/executable.py
mmp_metadata_client/models/execution.py
mmp_metadata_client/models/experiment.py
mmp_metadata_client/models/metrics.py
mmp_metadata_client/models/model.py
mmp_metadata_client/models/pair.py
mmp_metadata_client/models/pipeline.py
mmp_metadata_client/models/run.py
mmp_metadata_client/models/trace.py
mmp_metadata_client/models/trace_artifacts.py
mmp_metadata_client/models/trace_execution_types.py
mmp_metadata_client/models/workflow.py
mmp_metadata_client/models/workflow_node.py
test/__init__.py
test/test_artifact.py
test/test_artifact_api.py
test/test_dataset.py
test/test_event.py
test/test_executable.py
test/test_execution.py
test/test_execution_api.py
test/test_experiment.py
test/test_experiment_api.py
test/test_metrics.py
test/test_model.py
test/test_pair.py
test/test_pipeline.py
test/test_run.py
test/test_run_api.py
test/test_trace.py
test/test_trace_api.py
test/test_trace_artifacts.py
test/test_trace_execution_types.py
test/test_workflow.py
test/test_workflow_api.py
test/test_workflow_node.py
mmp_metadata-1.1.3.dist-info/LICENSE
mmp_metadata-1.1.3.dist-info/METADATA
mmp_metadata-1.1.3.dist-info/WHEEL
mmp_metadata-1.1.3.dist-info/top_level.txt
mmp_metadata-1.1.3.dist-info/RECORD
