Metadata-Version: 2.1
Name: mmp-metadata
Version: 1.1.3
Summary: MMP Metadata
Home-page: https://www.ipvs.uni-stuttgart.d
Author: Matthias Popp
Author-email: st116848@stud.uni-stuttgart.de.com
License: UNKNOWN
Keywords: OpenAPI,OpenAPI-Generator,MMP Metadata
Platform: UNKNOWN
Requires-Dist: urllib3 (>=1.15)
Requires-Dist: six (>=1.10)
Requires-Dist: certifi
Requires-Dist: python-dateutil
